LICENSE
MANIFEST.in
README.rst
setup.py
lampwick/__init__.py
lampwick/encoding_options.py
lampwick/movie.py
lampwick/transcoder.py
lampwick.egg-info/PKG-INFO
lampwick.egg-info/SOURCES.txt
lampwick.egg-info/dependency_links.txt
lampwick.egg-info/requires.txt
lampwick.egg-info/top_level.txt
tests/__init__.py
tests/test_encoding_options.py
tests/test_movie.py