Metadata-Version: 1.1
Name: lampwick
Version: 0.2.1
Summary: Simple wrappper around ffmpeg commands.
Home-page: https://github.com/sdispater/lampwick
Author: Sébastien Eustace
Author-email: sebastien.eustace@gmail.com
License: MIT
Download-URL: https://github.com/sdispater/lampwick/archive/0.2.1.tar.gz
Platform: UNKNOWN
Classifier: Intended Audience :: Developers
Classifier: Operating System :: OS Independent
Classifier: Programming Language :: Python
Classifier: Topic :: Software Development :: Libraries :: Python Modules
